gnupg_mails/__init__.py
gnupg_mails/message.py
gnupg_mails/__pycache__/__init__.cpython-38.pyc
gnupg_mails/__pycache__/message.cpython-38.pyc
gnupg_mails/migrations/__init__.py
gnupg_mails/tests/__init__.py
gnupg_mails/tests/test_message.py
gnupg_mails/tests/test_settings.py
gnupg_mails/tests/__pycache__/__init__.cpython-38.pyc
gnupg_mails/tests/__pycache__/test_message.cpython-38.pyc
gnupg_mails/tests/__pycache__/test_settings.cpython-38.pyc
django_gnupg_mails-0.4.0.dist-info/AUTHORS
django_gnupg_mails-0.4.0.dist-info/LICENSE
django_gnupg_mails-0.4.0.dist-info/METADATA
django_gnupg_mails-0.4.0.dist-info/WHEEL
django_gnupg_mails-0.4.0.dist-info/top_level.txt
django_gnupg_mails-0.4.0.dist-info/RECORD
