Metadata-Version: 2.1
Name: django-gnupg-mails
Version: 0.4.0
Summary: A Django reusable app providing the ability to send PGP/MIME signed multipart emails.
Home-page: https://github.com/jandd/django-gnupg-mails
Author: Jan Dittberner
Author-email: jan@dittberner.info
License: UNKNOWN
Platform: UNKNOWN
Classifier: Development Status :: 5 - Production/Stable
Classifier: Environment :: Web Environment
Classifier: Intended Audience :: Developers
Classifier: Operating System :: OS Independent
Classifier: Programming Language :: Python :: 3
Classifier: Programming Language :: Python :: 3.5
Classifier: Programming Language :: Python :: 3.6
Classifier: Programming Language :: Python :: 3.7
Classifier: Programming Language :: Python :: 3.8
Classifier: Framework :: Django
Classifier: Topic :: Communications :: Email
Classifier: Topic :: Security :: Cryptography
Requires-Python: >=3.5
Requires-Dist: Django
Requires-Dist: python-gnupg
Requires-Dist: sphinx-me
